ascend_great_expectations_gcs/__init__.py
ascend_great_expectations_gcs/validator.py
ascend_great_expectations_gcs-0.2.5.dist-info/LICENSE
ascend_great_expectations_gcs-0.2.5.dist-info/METADATA
ascend_great_expectations_gcs-0.2.5.dist-info/WHEEL
ascend_great_expectations_gcs-0.2.5.dist-info/top_level.txt
ascend_great_expectations_gcs-0.2.5.dist-info/RECORD
