Metadata-Version: 2.1
Name: ascend-great-expectations-gcs
Version: 0.2.5
Summary: A wrapper around Great Expectations for building validation components in Ascend.io platform
Home-page: UNKNOWN
License: UNKNOWN
Platform: UNKNOWN
Requires-Python: >=3.7
License-File: LICENSE
Requires-Dist: great-expectations
Requires-Dist: google-cloud-storage
Requires-Dist: looker-sdk
